setup.py
brtools.egg-info/PKG-INFO
brtools.egg-info/SOURCES.txt
brtools.egg-info/dependency_links.txt
brtools.egg-info/top_level.txt
brtools_histology/__init__.py