Metadata-Version: 1.1
Name: brtools
Version: 0.0.1
Summary: Does something and then we make money
Home-page: https://bitbucket.org/seanroark/brtools_histology.git
Author: Sean and Matt
Author-email: mattthebaer@gmail.com
License: UNKNOWN
Platform: UNKNOWN
Classifier: Programming Language :: Python
Classifier: Programming Language :: Python :: 2
Classifier: License :: OSI Approved :: GNU General Public License (GPL)
Classifier: Operating System :: OS Independent
Classifier: Development Status :: 1 - Planning
Classifier: Environment :: Console
Classifier: Intended Audience :: Science/Research
Classifier: Topic :: Scientific/Engineering :: GIS
